{
  "hash": "63a0b0bf",
  "configHash": "8c066f58",
  "lockfileHash": "0538ce50",
  "browserHash": "f76e5f11",
  "optimized": {
    "react": {
      "src": "../../node_modules/react/index.js",
      "file": "react.js",
      "fileHash": "c31c35a2",
      "needsInterop": true
    },
    "react-dom/client": {
      "src": "../../node_modules/react-dom/client.js",
      "file": "react-dom_client.js",
      "fileHash": "bd624735",
      "needsInterop": true
    },
    "react-router-dom": {
      "src": "../../node_modules/react-router-dom/dist/index.mjs",
      "file": "react-router-dom.js",
      "fileHash": "16188326",
      "needsInterop": false
    },
    "lucide-react": {
      "src": "../../node_modules/lucide-react/dist/esm/lucide-react.js",
      "file": "lucide-react.js",
      "fileHash": "670be0fe",
      "needsInterop": false
    },
    "axios": {
      "src": "../../node_modules/axios/index.js",
      "file": "axios.js",
      "fileHash": "38457225",
      "needsInterop": false
    }
  },
  "chunks": {
    "chunk-3HME3SJ2": {
      "file": "chunk-3HME3SJ2.js"
    },
    "chunk-GH6UE3LJ": {
      "file": "chunk-GH6UE3LJ.js"
    },
    "chunk-G3PMV62Z": {
      "file": "chunk-G3PMV62Z.js"
    }
  }
}